sequence_label/__about__.py
sequence_label/__init__.py
sequence_label/core.py
sequence_label/py.typed
sequence_label/transformers/__init__.py
sequence_label/transformers/core.py
sequence_label-0.1.8.dist-info/METADATA
sequence_label-0.1.8.dist-info/WHEEL
sequence_label-0.1.8.dist-info/licenses/LICENSE
sequence_label-0.1.8.dist-info/RECORD
