Metadata-Version: 2.4
Name: sequence-label
Version: 0.1.8
Summary: A Tensor Creation and Label Reconstruction for Sequence Labeling
Author-email: Yasufumi Taniguchi <yasufumi.taniguchi@gmail.com>
License: MIT
License-File: LICENSE
Classifier: Programming Language :: Python
Classifier: Programming Language :: Python :: 3.10
Classifier: Programming Language :: Python :: 3.11
Classifier: Programming Language :: Python :: 3.12
Classifier: Programming Language :: Python :: 3.13
Requires-Python: <3.14,>=3.10
Provides-Extra: ci
Requires-Dist: black<24,>=23.7.0; extra == 'ci'
Requires-Dist: hypothesis<7,>=6.86.2; extra == 'ci'
Requires-Dist: mypy<2,>=1.5.0; extra == 'ci'
Requires-Dist: pytest-cov<5,>=4.1.0; extra == 'ci'
Requires-Dist: pytest<8,>=7.4.0; extra == 'ci'
Requires-Dist: ruff>=0.2.0; extra == 'ci'
Requires-Dist: transformers<5,>=4.31.0; extra == 'ci'
Provides-Extra: dev
Requires-Dist: black<24,>=23.7.0; extra == 'dev'
Requires-Dist: hypothesis<7,>=6.86.2; extra == 'dev'
Requires-Dist: ipdb<0.14,>=0.13.13; extra == 'dev'
Requires-Dist: ipython<9,>=8.14.0; extra == 'dev'
Requires-Dist: mypy<2,>=1.5.0; extra == 'dev'
Requires-Dist: pytest-cov<5,>=4.1.0; extra == 'dev'
Requires-Dist: pytest<8,>=7.4.0; extra == 'dev'
Requires-Dist: ruff>=0.2.0; extra == 'dev'
Requires-Dist: transformers<5,>=4.31.0; extra == 'dev'
Provides-Extra: transformers
Requires-Dist: transformers<5,>=4.31.0; extra == 'transformers'
